{"news":[
 {"path":"news05.jpg","tit":"기사 사진5", "tit2":"이마트24, 이번엔 3백만원 노래박스, BMW 미니쿠퍼 판매!", "href":"https://www.shinsegaegroupnewsroom.com/100823/", "ndate":"2023. 03. 06"},
 {"path":"news06.png","tit":"기사 사진6", "tit2":"이마트, 1억원 상당의 시각장애인용 점자 패드 기부", "href":"https://www.shinsegaegroupnewsroom.com/100808/", "ndate":"2023. 03. 06"},
 {"path":"news07.png","tit":"기사 사진7", "tit2":"이마트24, 개강 시즌 ‘화이트데이’ 맞아 파격 경품행사 진행!", "href":"https://www.shinsegaegroupnewsroom.com/100785/", "ndate":"2023. 03. 06"},
 {"path":"news08.png","tit":"기사 사진8", "tit2":"이마트에브리데이, 삼겹살데이 맞아 삼겹살·목심 최대 40% 할인", "href":"https://www.shinsegaegroupnewsroom.com/100623/", "ndate":"2023. 03. 03"}
 ]}

